<?xml version="1.0" encoding="utf-8"?>
<!--Detailed report on module ImmutableStringFieldGenerator-->
<CCCC_Project>
<module_summary>
<lines_of_code value="33" level="0" />
<lines_of_code_per_member_function value="******" level="0" />
<McCabes_cyclomatic_complexity value="0" level="0" />
<McCabes_cyclomatic_complexity_per_member_function value="******" level="0" />
<lines_of_code value="1" level="0" />
<lines_of_code_per_member_function value="********" level="2" />
<lines_of_code_per_line_of_comment value="33.000" level="2" />
<McCabes_cyclomatic_complexity_per_line_of_comment value="------" level="0" />
<weighted_methods_per_class_unity value="20" level="0" />
<weighted_methods_per_class_visibility value="4" level="0" />
<depth_of_inheritance_tree value="1" level="0" />
<number_of_children value="1" level="0" />
<coupling_between_objects value="7" level="0" />
<IF4 value="36" level="0" />
<IF4_per_member_function value="********" level="2" />
<IF4_visible value="36" level="1" />
<IF4_visible_per_member_function value="********" level="2" />
<IF4_concrete value="4" level="0" />
<IF4_concrete_per_member_function value="********" level="2" />
</module_summary>
<module_detail>
<description>definition</description>
<source_reference file="./lib/protobuf/src/google/protobuf/compiler/java/java_string_field.h" line="57" />
<lines_of_code value="11" level="0" />
<McCabes_cyclomatic_complexity value="0" level="0" />
<lines_of_comment value="0" level="0" />
<lines_of_code_per_line_of_comment value="------" level="0" />
<McCabes_cyclomatic_complexity_per_line_of_comment value="------" level="0" />
</module_detail>
<procedural_detail>
<member_function>
<name>GOOGLE_DISALLOW_EVIL_CONSTRUCTORS(ImmutableStringFieldGenerator)</name>
<extent>
<description>declaration</description>
<source_reference file="./lib/protobuf/src/google/protobuf/compiler/java/java_string_field.h" line="93" />
</extent>
<lines_of_code value="1" level="0" />
<McCabes_cyclomatic_complexity value="0" level="0" />
<lines_of_comment value="0" level="0" />
<lines_of_code_per_line_of_comment value="------" level="0" />
<McCabes_cyclomatic_complexity_per_line_of_comment value="------" level="0" />
</member_function>
<member_function>
<name>GenerateBuilderClearCode(Printer *)</name>
<extent>
<description>declaration</description>
<source_reference file="./lib/protobuf/src/google/protobuf/compiler/java/java_string_field.h" line="71" />
</extent>
<lines_of_code value="1" level="0" />
<McCabes_cyclomatic_complexity value="0" level="0" />
<lines_of_comment value="0" level="0" />
<lines_of_code_per_line_of_comment value="------" level="0" />
<McCabes_cyclomatic_complexity_per_line_of_comment value="------" level="0" />
</member_function>
<member_function>
<name>GenerateBuilderMembers(Printer *)</name>
<extent>
<description>declaration</description>
<source_reference file="./lib/protobuf/src/google/protobuf/compiler/java/java_string_field.h" line="69" />
</extent>
<lines_of_code value="1" level="0" />
<McCabes_cyclomatic_complexity value="0" level="0" />
<lines_of_comment value="0" level="0" />
<lines_of_code_per_line_of_comment value="------" level="0" />
<McCabes_cyclomatic_complexity_per_line_of_comment value="------" level="0" />
</member_function>
<member_function>
<name>GenerateBuildingCode(Printer *)</name>
<extent>
<description>declaration</description>
<source_reference file="./lib/protobuf/src/google/protobuf/compiler/java/java_string_field.h" line="73" />
</extent>
<lines_of_code value="1" level="0" />
<McCabes_cyclomatic_complexity value="0" level="0" />
<lines_of_comment value="0" level="0" />
<lines_of_code_per_line_of_comment value="------" level="0" />
<McCabes_cyclomatic_complexity_per_line_of_comment value="------" level="0" />
</member_function>
<member_function>
<name>GenerateEqualsCode(Printer *)</name>
<extent>
<description>declaration</description>
<source_reference file="./lib/protobuf/src/google/protobuf/compiler/java/java_string_field.h" line="79" />
</extent>
<lines_of_code value="1" level="0" />
<McCabes_cyclomatic_complexity value="0" level="0" />
<lines_of_comment value="0" level="0" />
<lines_of_code_per_line_of_comment value="------" level="0" />
<McCabes_cyclomatic_complexity_per_line_of_comment value="------" level="0" />
</member_function>
<member_function>
<name>GenerateFieldBuilderInitializationCode(Printer *)</name>
<extent>
<description>declaration</description>
<source_reference file="./lib/protobuf/src/google/protobuf/compiler/java/java_string_field.h" line="78" />
</extent>
<lines_of_code value="1" level="0" />
<McCabes_cyclomatic_complexity value="0" level="0" />
<lines_of_comment value="0" level="0" />
<lines_of_code_per_line_of_comment value="------" level="0" />
<McCabes_cyclomatic_complexity_per_line_of_comment value="------" level="0" />
</member_function>
<member_function>
<name>GenerateHashCode(Printer *)</name>
<extent>
<description>declaration</description>
<source_reference file="./lib/protobuf/src/google/protobuf/compiler/java/java_string_field.h" line="80" />
</extent>
<lines_of_code value="1" level="0" />
<McCabes_cyclomatic_complexity value="0" level="0" />
<lines_of_comment value="0" level="0" />
<lines_of_code_per_line_of_comment value="------" level="0" />
<McCabes_cyclomatic_complexity_per_line_of_comment value="------" level="0" />
</member_function>
<member_function>
<name>GenerateInitializationCode(Printer *)</name>
<extent>
<description>declaration</description>
<source_reference file="./lib/protobuf/src/google/protobuf/compiler/java/java_string_field.h" line="70" />
</extent>
<lines_of_code value="1" level="0" />
<McCabes_cyclomatic_complexity value="0" level="0" />
<lines_of_comment value="0" level="0" />
<lines_of_code_per_line_of_comment value="------" level="0" />
<McCabes_cyclomatic_complexity_per_line_of_comment value="------" level="0" />
</member_function>
<member_function>
<name>GenerateInterfaceMembers(Printer *)</name>
<extent>
<description>declaration</description>
<source_reference file="./lib/protobuf/src/google/protobuf/compiler/java/java_string_field.h" line="67" />
</extent>
<lines_of_code value="1" level="0" />
<McCabes_cyclomatic_complexity value="0" level="0" />
<lines_of_comment value="0" level="0" />
<lines_of_code_per_line_of_comment value="------" level="0" />
<McCabes_cyclomatic_complexity_per_line_of_comment value="------" level="0" />
</member_function>
<member_function>
<name>GenerateMembers(Printer *)</name>
<extent>
<description>declaration</description>
<source_reference file="./lib/protobuf/src/google/protobuf/compiler/java/java_string_field.h" line="68" />
</extent>
<lines_of_code value="1" level="0" />
<McCabes_cyclomatic_complexity value="0" level="0" />
<lines_of_comment value="0" level="0" />
<lines_of_code_per_line_of_comment value="------" level="0" />
<McCabes_cyclomatic_complexity_per_line_of_comment value="------" level="0" />
</member_function>
<member_function>
<name>GenerateMergingCode(Printer *)</name>
<extent>
<description>declaration</description>
<source_reference file="./lib/protobuf/src/google/protobuf/compiler/java/java_string_field.h" line="72" />
</extent>
<lines_of_code value="1" level="0" />
<McCabes_cyclomatic_complexity value="0" level="0" />
<lines_of_comment value="0" level="0" />
<lines_of_code_per_line_of_comment value="------" level="0" />
<McCabes_cyclomatic_complexity_per_line_of_comment value="------" level="0" />
</member_function>
<member_function>
<name>GenerateParsingCode(Printer *)</name>
<extent>
<description>declaration</description>
<source_reference file="./lib/protobuf/src/google/protobuf/compiler/java/java_string_field.h" line="74" />
</extent>
<lines_of_code value="1" level="0" />
<McCabes_cyclomatic_complexity value="0" level="0" />
<lines_of_comment value="0" level="0" />
<lines_of_code_per_line_of_comment value="------" level="0" />
<McCabes_cyclomatic_complexity_per_line_of_comment value="------" level="0" />
</member_function>
<member_function>
<name>GenerateParsingDoneCode(Printer *)</name>
<extent>
<description>declaration</description>
<source_reference file="./lib/protobuf/src/google/protobuf/compiler/java/java_string_field.h" line="75" />
</extent>
<lines_of_code value="1" level="0" />
<McCabes_cyclomatic_complexity value="0" level="0" />
<lines_of_comment value="0" level="0" />
<lines_of_code_per_line_of_comment value="------" level="0" />
<McCabes_cyclomatic_complexity_per_line_of_comment value="------" level="0" />
</member_function>
<member_function>
<name>GenerateSerializationCode(Printer *)</name>
<extent>
<description>declaration</description>
<source_reference file="./lib/protobuf/src/google/protobuf/compiler/java/java_string_field.h" line="76" />
</extent>
<lines_of_code value="1" level="0" />
<McCabes_cyclomatic_complexity value="0" level="0" />
<lines_of_comment value="0" level="0" />
<lines_of_code_per_line_of_comment value="------" level="0" />
<McCabes_cyclomatic_complexity_per_line_of_comment value="------" level="0" />
</member_function>
<member_function>
<name>GenerateSerializedSizeCode(Printer *)</name>
<extent>
<description>declaration</description>
<source_reference file="./lib/protobuf/src/google/protobuf/compiler/java/java_string_field.h" line="77" />
</extent>
<lines_of_code value="1" level="0" />
<McCabes_cyclomatic_complexity value="0" level="0" />
<lines_of_comment value="0" level="0" />
<lines_of_code_per_line_of_comment value="------" level="0" />
<McCabes_cyclomatic_complexity_per_line_of_comment value="------" level="0" />
</member_function>
<member_function>
<name>GetBoxedType()</name>
<extent>
<description>declaration</description>
<source_reference file="./lib/protobuf/src/google/protobuf/compiler/java/java_string_field.h" line="82" />
</extent>
<lines_of_code value="1" level="0" />
<McCabes_cyclomatic_complexity value="0" level="0" />
<lines_of_comment value="0" level="0" />
<lines_of_code_per_line_of_comment value="------" level="0" />
<McCabes_cyclomatic_complexity_per_line_of_comment value="------" level="0" />
</member_function>
<member_function>
<name>GetNumBitsForBuilder()</name>
<extent>
<description>declaration</description>
<source_reference file="./lib/protobuf/src/google/protobuf/compiler/java/java_string_field.h" line="66" />
</extent>
<lines_of_code value="1" level="0" />
<McCabes_cyclomatic_complexity value="0" level="0" />
<lines_of_comment value="0" level="0" />
<lines_of_code_per_line_of_comment value="------" level="0" />
<McCabes_cyclomatic_complexity_per_line_of_comment value="------" level="0" />
</member_function>
<member_function>
<name>GetNumBitsForMessage()</name>
<extent>
<description>declaration</description>
<source_reference file="./lib/protobuf/src/google/protobuf/compiler/java/java_string_field.h" line="65" />
</extent>
<lines_of_code value="1" level="0" />
<McCabes_cyclomatic_complexity value="0" level="0" />
<lines_of_comment value="1" level="0" />
<lines_of_code_per_line_of_comment value="------" level="0" />
<McCabes_cyclomatic_complexity_per_line_of_comment value="------" level="0" />
</member_function>
<member_function>
<name>ImmutableStringFieldGenerator(const FieldDescriptor *,int,int,Context *)</name>
<extent>
<description>declaration</description>
<source_reference file="./lib/protobuf/src/google/protobuf/compiler/java/java_string_field.h" line="59" />
</extent>
<lines_of_code value="3" level="0" />
<McCabes_cyclomatic_complexity value="0" level="0" />
<lines_of_comment value="0" level="0" />
<lines_of_code_per_line_of_comment value="------" level="0" />
<McCabes_cyclomatic_complexity_per_line_of_comment value="------" level="0" />
</member_function>
<member_function>
<name>~ImmutableStringFieldGenerator()</name>
<extent>
<description>declaration</description>
<source_reference file="./lib/protobuf/src/google/protobuf/compiler/java/java_string_field.h" line="62" />
</extent>
<lines_of_code value="1" level="0" />
<McCabes_cyclomatic_complexity value="0" level="0" />
<lines_of_comment value="0" level="0" />
<lines_of_code_per_line_of_comment value="------" level="0" />
<McCabes_cyclomatic_complexity_per_line_of_comment value="------" level="0" />
</member_function>
</procedural_detail>
<structural_detail>
<module>
<name>ImmutableStringFieldGenerator</name>
<client_module>
<name>ImmutableStringOneofFieldGenerator</name>
<visible>true</visible>
<concrete>true</concrete>
<extent>
<description>inheritance</description>
<source_reference file="./lib/protobuf/src/google/protobuf/compiler/java/java_string_field.h" line="97" />
</extent>
</client_module>
<supplier_module>
<name>ClassNameResolver</name>
<visible>true</visible>
<concrete>false</concrete>
<extent>
<description>has by reference</description>
<source_reference file="./lib/protobuf/src/google/protobuf/compiler/java/java_string_field.h" line="90" />
</extent>
<name>Context</name>
<visible>true</visible>
<concrete>false</concrete>
<extent>
<description>pass by reference</description>
<source_reference file="./lib/protobuf/src/google/protobuf/compiler/java/java_string_field.h" line="61" />
</extent>
<extent>
<description>has by reference</description>
<source_reference file="./lib/protobuf/src/google/protobuf/compiler/java/java_string_field.h" line="89" />
</extent>
<name>FieldDescriptor</name>
<visible>true</visible>
<concrete>false</concrete>
<extent>
<description>pass by reference</description>
<source_reference file="./lib/protobuf/src/google/protobuf/compiler/java/java_string_field.h" line="60" />
</extent>
<extent>
<description>has by reference</description>
<source_reference file="./lib/protobuf/src/google/protobuf/compiler/java/java_string_field.h" line="85" />
</extent>
<name>ImmutableFieldGenerator</name>
<visible>true</visible>
<concrete>true</concrete>
<extent>
<description>inheritance</description>
<source_reference file="./lib/protobuf/src/google/protobuf/compiler/java/java_string_field.h" line="57" />
</extent>
<name>Printer</name>
<visible>true</visible>
<concrete>false</concrete>
<extent>
<description>pass by reference</description>
<source_reference file="./lib/protobuf/src/google/protobuf/compiler/java/java_string_field.h" line="67" />
</extent>
<extent>
<description>pass by reference</description>
<source_reference file="./lib/protobuf/src/google/protobuf/compiler/java/java_string_field.h" line="68" />
</extent>
<extent>
<description>pass by reference</description>
<source_reference file="./lib/protobuf/src/google/protobuf/compiler/java/java_string_field.h" line="69" />
</extent>
<extent>
<description>pass by reference</description>
<source_reference file="./lib/protobuf/src/google/protobuf/compiler/java/java_string_field.h" line="70" />
</extent>
<extent>
<description>pass by reference</description>
<source_reference file="./lib/protobuf/src/google/protobuf/compiler/java/java_string_field.h" line="71" />
</extent>
<extent>
<description>pass by reference</description>
<source_reference file="./lib/protobuf/src/google/protobuf/compiler/java/java_string_field.h" line="72" />
</extent>
<extent>
<description>pass by reference</description>
<source_reference file="./lib/protobuf/src/google/protobuf/compiler/java/java_string_field.h" line="73" />
</extent>
<extent>
<description>pass by reference</description>
<source_reference file="./lib/protobuf/src/google/protobuf/compiler/java/java_string_field.h" line="74" />
</extent>
<extent>
<description>pass by reference</description>
<source_reference file="./lib/protobuf/src/google/protobuf/compiler/java/java_string_field.h" line="75" />
</extent>
<extent>
<description>pass by reference</description>
<source_reference file="./lib/protobuf/src/google/protobuf/compiler/java/java_string_field.h" line="76" />
</extent>
<extent>
<description>pass by reference</description>
<source_reference file="./lib/protobuf/src/google/protobuf/compiler/java/java_string_field.h" line="77" />
</extent>
<extent>
<description>pass by reference</description>
<source_reference file="./lib/protobuf/src/google/protobuf/compiler/java/java_string_field.h" line="78" />
</extent>
<extent>
<description>pass by reference</description>
<source_reference file="./lib/protobuf/src/google/protobuf/compiler/java/java_string_field.h" line="79" />
</extent>
<extent>
<description>pass by reference</description>
<source_reference file="./lib/protobuf/src/google/protobuf/compiler/java/java_string_field.h" line="80" />
</extent>
<name>map</name>
<visible>true</visible>
<concrete>true</concrete>
<extent>
<description>has by value</description>
<source_reference file="./lib/protobuf/src/google/protobuf/compiler/java/java_string_field.h" line="86" />
</extent>
</supplier_module>
</module>
</structural_detail>
</CCCC_Project>
